nextmock/__init__.py
nextmock/arg.py
nextmock/async_mock.py
nextmock/fake.py
nextmock/mock.py
nextmock/test/__init__.py
nextmock/test/test_async_mock.py
nextmock/test/test_mock_class.py
nextmock/test/test_mock_compatibility.py
nextmock/test/test_mock_raises.py
nextmock/test/test_mock_returns.py
nextmock/test/test_mock_with_args.py
nextmock-0.0.1.dist-info/LICENSE
nextmock-0.0.1.dist-info/METADATA
nextmock-0.0.1.dist-info/WHEEL
nextmock-0.0.1.dist-info/top_level.txt
nextmock-0.0.1.dist-info/RECORD
