Metadata-Version: 2.1
Name: nextmock
Version: 0.0.1
Summary: NextMock is an enhanced mock for unittest.mock.Mock
Home-page: https://github.com/pilagod/nextmock
Author: pilagod
Author-email: pilagooood@gmail.com
License: MIT
Project-URL: Documentation, https://github.com/pilagod/nextmock
Project-URL: Source, https://github.com/pilagod/nextmock
Project-URL: Tracker, https://github.com/pilagod/nextmock/issues
Keywords: testing unit mock
Platform: UNKNOWN
Classifier: License :: OSI Approved :: MIT License
Classifier: Operating System :: OS Independent
Classifier: Programming Language :: Python :: 3
Classifier: Programming Language :: Python :: 3.6
Classifier: Programming Language :: Python :: 3.7
Classifier: Programming Language :: Python :: 3.8
Classifier: Programming Language :: Python :: 3.9
Classifier: Topic :: Software Development :: Testing
Classifier: Topic :: Software Development :: Testing :: Mocking
Classifier: Topic :: Software Development :: Testing :: Unit
Requires-Python: >=3.6
